android_auto_play_opencv/AapoManager.py
android_auto_play_opencv/Adblib.py
android_auto_play_opencv/MatchTemplateLib.py
android_auto_play_opencv/__init__.py
android_auto_play_opencv-1.0.9.dist-info/METADATA
android_auto_play_opencv-1.0.9.dist-info/WHEEL
android_auto_play_opencv-1.0.9.dist-info/top_level.txt
android_auto_play_opencv-1.0.9.dist-info/RECORD
