Metadata-Version: 2.1
Name: android_auto_play_opencv
Version: 1.0.9
Summary: Operate Android using OpenCV.
Home-page: https://github.com/noitaro/android-auto-play-opencv
Author: noita
Author-email: noitalog.tokyo@gmail.com
License: MIT
Keywords: android auto play opencv
Classifier: License :: OSI Approved :: MIT License
Classifier: Programming Language :: Python :: 3.7
Requires-Dist: opencv-python
Requires-Dist: numpy
